<?xml version="1.0" encoding="windows-1252" ?>
<!DOCTYPE ViewLink SYSTEM "jbo_03_01.dtd">
<!---->
<ViewLink
  xmlns="http://xmlns.oracle.com/bc4j"
  Name="FkIgpMPoLink"
  Version="12.2.1.11.57"
  InheritPersonalization="merge"
  EntityAssociation="model.ERP.EO.FkIgpMPoAssoc">
  <ViewLinkDefEnd
    Name="TblPoMView"
    Cardinality="1"
    Source="true"
    Owner="model.ERP.VO.TblPoMView">
    <DesignTime>
      <Attr Name="_isUpdateable" Value="true"/>
      <Attr Name="_finderName" Value="TblPoMView"/>
    </DesignTime>
    <AttrArray Name="Attributes">
      <Item Value="model.ERP.VO.TblPoMView.Id"/>
    </AttrArray>
  </ViewLinkDefEnd>
  <ViewLinkDefEnd
    Name="TblIgpMView"
    Cardinality="-1"
    Owner="model.ERP.VO.TblIgpMView">
    <DesignTime>
      <Attr Name="_isUpdateable" Value="true"/>
      <Attr Name="_finderName" Value="TblIgpMView"/>
    </DesignTime>
    <AttrArray Name="Attributes">
      <Item Value="model.ERP.VO.TblIgpMView.PoMId"/>
    </AttrArray>
  </ViewLinkDefEnd>
</ViewLink>
