<?xml version="1.0" encoding="windows-1252" ?>
<!DOCTYPE ViewObject SYSTEM "jbo_03_01.dtd">
<!---->
<ViewObject
  xmlns="http://xmlns.oracle.com/bc4j"
  Name="TblStdApplPrncpl"
  Version="12.2.1.11.57"
  InheritPersonalization="merge"
  BindingStyle="OracleName"
  CustomQuery="false"
  PageIterMode="Full"
  SelectList="TblStdAppl.AMOUNT, 
       TblStdAppl.APPL_REASON, 
       TblStdAppl.APPL_STATUS, 
       TblStdAppl.APPL_TYPE, 
       TblStdAppl.CREATED_BY, 
       TblStdAppl.CREATED_DATE, 
       TblStdAppl.DATED, 
       TblStdAppl.FEE_GEN_DETAIL_ID, 
       TblStdAppl.FROM_DATE, 
       TblStdAppl.ID, 
       TblStdAppl.MGT_REMARKS, 
       TblStdAppl.PRINC_REMARKS, 
       TblStdAppl.STD_REG_ID, 
       TblStdAppl.TO_DATE, 
       TblStdAppl.UPDATED_BY, 
       TblStdAppl.UPDATED_DATE, 
       TblStdAppl.COMPANY_SBU_ID"
  FromList="TBL_STD_APPL TblStdAppl"
  Where="TblStdAppl.APPL_STATUS = 'mgr' 
AND  TblStdAppl.COMPANY_SBU_ID= nvl(:getcompid,TblStdAppl.COMPANY_SBU_ID)">
  <Properties>
    <SchemaBasedProperties>
      <LABEL
        ResId="model.ERP.VO.TblStdApplPrncpl_LABEL"/>
    </SchemaBasedProperties>
  </Properties>
  <Variable
    Name="getcompid"
    Kind="where"
    Type="java.math.BigDecimal">
    <TransientExpression
      Name="VariableScript"
      trustMode="trusted"
      CodeSourceName="TblStdApplPrncpl"/>
  </Variable>
  <ViewAccessor
    Name="Student_Appl_Appr_Prncpl_Status1"
    ViewObjectName="model.LOV.Student_Appl_Appr_Prncpl_Status"
    RowLevelBinds="true"/>
  <ListBinding
    Name="LOV_ApplStatus"
    ListVOName="Student_Appl_Appr_Prncpl_Status1"
    ListRangeSize="-1"
    NullValueFlag="none"
    MRUCount="0">
    <AttrArray Name="AttrNames">
      <Item Value="ApplStatus"/>
    </AttrArray>
    <AttrArray Name="AttrExpressions"/>
    <AttrArray Name="ListAttrNames">
      <Item Value="dbValue"/>
    </AttrArray>
    <AttrArray Name="ListDisplayAttrNames">
      <Item Value="ViewAttr"/>
    </AttrArray>
    <DisplayCriteria/>
  </ListBinding>
  <EntityUsage
    Name="TblStdAppl"
    Entity="model.ERP.EO.TblStdAppl"/>
  <ViewAttribute
    Name="Amount"
    PrecisionRule="true"
    EntityAttrName="Amount"
    EntityUsage="TblStdAppl"
    AliasName="AMOUNT"/>
  <ViewAttribute
    Name="ApplReason"
    PrecisionRule="true"
    EntityAttrName="ApplReason"
    EntityUsage="TblStdAppl"
    AliasName="APPL_REASON"/>
  <ViewAttribute
    Name="ApplStatus"
    PrecisionRule="true"
    EntityAttrName="ApplStatus"
    EntityUsage="TblStdAppl"
    AliasName="APPL_STATUS"
    LOVName="LOV_ApplStatus">
    <Properties>
      <SchemaBasedProperties>
        <CONTROLTYPE
          Value="combo"/>
      </SchemaBasedProperties>
    </Properties>
  </ViewAttribute>
  <ViewAttribute
    Name="ApplType"
    PrecisionRule="true"
    EntityAttrName="ApplType"
    EntityUsage="TblStdAppl"
    AliasName="APPL_TYPE"/>
  <ViewAttribute
    Name="CreatedBy"
    PrecisionRule="true"
    EntityAttrName="CreatedBy"
    EntityUsage="TblStdAppl"
    AliasName="CREATED_BY"/>
  <ViewAttribute
    Name="CreatedDate"
    PrecisionRule="true"
    EntityAttrName="CreatedDate"
    EntityUsage="TblStdAppl"
    AliasName="CREATED_DATE"
    IsUpdateable="false"/>
  <ViewAttribute
    Name="Dated"
    PrecisionRule="true"
    EntityAttrName="Dated"
    EntityUsage="TblStdAppl"
    AliasName="DATED"/>
  <ViewAttribute
    Name="FeeGenDetailId"
    PrecisionRule="true"
    EntityAttrName="FeeGenDetailId"
    EntityUsage="TblStdAppl"
    AliasName="FEE_GEN_DETAIL_ID"/>
  <ViewAttribute
    Name="FromDate"
    PrecisionRule="true"
    EntityAttrName="FromDate"
    EntityUsage="TblStdAppl"
    AliasName="FROM_DATE"/>
  <ViewAttribute
    Name="Id"
    PrecisionRule="true"
    EntityAttrName="Id"
    EntityUsage="TblStdAppl"
    AliasName="ID"/>
  <ViewAttribute
    Name="MgtRemarks"
    PrecisionRule="true"
    EntityAttrName="MgtRemarks"
    EntityUsage="TblStdAppl"
    AliasName="MGT_REMARKS"/>
  <ViewAttribute
    Name="PrincRemarks"
    PrecisionRule="true"
    EntityAttrName="PrincRemarks"
    EntityUsage="TblStdAppl"
    AliasName="PRINC_REMARKS"/>
  <ViewAttribute
    Name="StdRegId"
    PrecisionRule="true"
    EntityAttrName="StdRegId"
    EntityUsage="TblStdAppl"
    AliasName="STD_REG_ID"/>
  <ViewAttribute
    Name="ToDate"
    PrecisionRule="true"
    EntityAttrName="ToDate"
    EntityUsage="TblStdAppl"
    AliasName="TO_DATE"/>
  <ViewAttribute
    Name="UpdatedBy"
    PrecisionRule="true"
    EntityAttrName="UpdatedBy"
    EntityUsage="TblStdAppl"
    AliasName="UPDATED_BY"/>
  <ViewAttribute
    Name="UpdatedDate"
    PrecisionRule="true"
    EntityAttrName="UpdatedDate"
    EntityUsage="TblStdAppl"
    AliasName="UPDATED_DATE"
    IsUpdateable="false"/>
  <ViewAttribute
    Name="CompanySbuId"
    PrecisionRule="true"
    EntityAttrName="CompanySbuId"
    EntityUsage="TblStdAppl"
    AliasName="COMPANY_SBU_ID"/>
  <ResourceBundle>
    <PropertiesBundle
      PropertiesFile="model.ModelBundle"/>
  </ResourceBundle>
</ViewObject>
