<?xml version="1.0" encoding="UTF-8" ?>
<pageDefinition xmlns="http://xmlns.oracle.com/adfm/uimodel" version="12.2.1.11.57" id="Cash_Receipt_VoucherPageDef"
                Package="Fragments.Group.Company.SBU.Modules.General_Ledger.Transaction">
  <parameters/>
 <executables>
    <variableIterator id="variables"/>
    <iterator Binds="USERS_CRUD_OPERATIONS1" RangeSize="25" DataControl="AppModuleDataControl"
              id="USERS_CRUD_OPERATIONS1Iterator"/>
    <iterator Binds="TblCrvMView1" RangeSize="8" DataControl="AppModuleDataControl1" id="TblCrvMView1Iterator"/>
    <searchRegion Binds="TblCrvMView1Iterator" Criteria=""
                  Customizer="oracle.jbo.uicli.binding.JUSearchBindingCustomizer" id="TblCrvMView1Query"/>
    <iterator Binds="TblCrvDView2" RangeSize="8" DataControl="AppModuleDataControl1" id="TblCrvDView2Iterator"/>
    <searchRegion Binds="TblCrvDView2Iterator" Criteria=""
                  Customizer="oracle.jbo.uicli.binding.JUSearchBindingCustomizer" id="TblCrvDView2Query"/>
  </executables>
  <bindings>
    <action id="Commit" RequiresUpdateModel="true" Action="commitTransaction" DataControl="AppModuleDataControl1"/>
    <action id="Rollback" RequiresUpdateModel="false" Action="rollbackTransaction" DataControl="AppModuleDataControl1"/>
    <tree IterBinding="USERS_CRUD_OPERATIONS1Iterator" id="USERS_CRUD_OPERATIONS1">
      <nodeDefinition DefName="model.UserRoles.VO.USERS_CRUD_OPERATIONS" Name="USERS_CRUD_OPERATIONS10">
        <AttrNames>
          <Item Value="Crudid"/>
          <Item Value="Operation"/>
          <Item Value="Icon"/>
          <Item Value="Bindingname"/>
          <Item Value="Btndisabled"/>
        </AttrNames>
      </nodeDefinition>
    </tree>
    <attributeValues IterBinding="TblCrvMView1Iterator" id="Id">
      <AttrNames>
        <Item Value="Id"/>
      </AttrNames>
    </attributeValues>
    <attributeValues IterBinding="TblCrvMView1Iterator" id="Vno">
      <AttrNames>
        <Item Value="Vno"/>
      </AttrNames>
    </attributeValues>
    <list IterBinding="TblCrvMView1Iterator" StaticList="false" Uses="LOV_Vtp" id="Vtp" DTSupportsMRU="false"
          SelectItemValueMode="ListObject"/>
    <attributeValues IterBinding="TblCrvMView1Iterator" id="Dated">
      <AttrNames>
        <Item Value="Dated"/>
      </AttrNames>
    </attributeValues>
    <attributeValues IterBinding="TblCrvMView1Iterator" id="Narration">
      <AttrNames>
        <Item Value="Narration"/>
      </AttrNames>
    </attributeValues>
    <list IterBinding="TblCrvMView1Iterator" StaticList="false" Uses="LOV_CompanySbuId" id="CompanySbuId"
          DTSupportsMRU="false" SelectItemValueMode="ListObject"/>
    
    <action IterBinding="TblCrvMView1Iterator" id="First" RequiresUpdateModel="true" Action="first"/>
    <action IterBinding="TblCrvMView1Iterator" id="Previous" RequiresUpdateModel="true" Action="previous"/>
    <action IterBinding="TblCrvMView1Iterator" id="Next" RequiresUpdateModel="true" Action="next"/>
    <action IterBinding="TblCrvMView1Iterator" id="Last" RequiresUpdateModel="true" Action="last"/>
    <action IterBinding="TblCrvMView1Iterator" id="CreateInsert" RequiresUpdateModel="true" Action="createInsertRow"/>
    <action IterBinding="TblCrvMView1Iterator" id="Execute" RequiresUpdateModel="true" Action="iteratorExecute"/>
    <action IterBinding="TblCrvMView1Iterator" id="Delete" RequiresUpdateModel="false" Action="removeCurrentRow"/>
    <tree IterBinding="TblCrvMView1Iterator" id="TblCrvMView1">
      <nodeDefinition DefName="model.ERP.VO.TblCrvMView" Name="TblCrvMView10">
        <AttrNames>
          <Item Value="Id"/>
          <Item Value="Vno"/>
          <Item Value="Vtp"/>
          <Item Value="Dated"/>
          <Item Value="Narration"/>
          <Item Value="CompanySbuId"/>
          
        </AttrNames>
      </nodeDefinition>
    </tree>
    <tree IterBinding="TblCrvDView2Iterator" id="TblCrvDView2">
      <nodeDefinition DefName="model.ERP.VO.TblCrvDView" Name="TblCrvDView20">
        <AttrNames>
          <Item Value="Id"/>
          <Item Value="SrNo"/>
          <Item Value="GlL4Id"/>
          <Item Value="Description"/>
          <Item Value="Dr"/>
          <Item Value="Cr"/>
        </AttrNames>
      </nodeDefinition>
    </tree>
    <action IterBinding="TblCrvDView2Iterator" id="CreateInsert1" RequiresUpdateModel="true" Action="createInsertRow"/>
    <action IterBinding="TblCrvDView2Iterator" id="Execute1" RequiresUpdateModel="true" Action="iteratorExecute"/>
    <action IterBinding="TblCrvDView2Iterator" id="Delete1" RequiresUpdateModel="false" Action="removeCurrentRow"/>
  </bindings>
</pageDefinition>
